.DS_Store
datacollector/__init__.py
datacollector/article.py
datacollector/datacollector_id.py
datacollector/datacollector_query.py
datacollector/datacollector_ui.py
datacollector/download.py
datacollector/ncbi.py
datacollector/test.py
datacollector/util.py
datacollector-0.0.7.dist-info/METADATA
datacollector-0.0.7.dist-info/WHEEL
datacollector-0.0.7.dist-info/top_level.txt
datacollector-0.0.7.dist-info/RECORD
