Metadata-Version: 2.1
Name: datacollector
Version: 0.0.7
Summary: PubMed article data collector
Home-page: UNKNOWN
Author: Kwok Sun Cheng
Author-email: <kwoksuncheng@unomaha.edu>
License: UNKNOWN
Keywords: python,PubMed,Data collector
Platform: UNKNOWN
Classifier: Intended Audience :: Education
Classifier: Programming Language :: Python :: 3
Classifier: Operating System :: MacOS :: MacOS X
Classifier: Operating System :: Microsoft :: Windows
Requires-Dist: beautifulsoup4
Requires-Dist: metapub
